<?xml version="1.0" encoding="UTF-8" standalone="no"?>
<catalog prefer="public" xmlns="urn:oasis:names:tc:entity:xmlns:xml:catalog">
    <group id="Folder Repository, directory=, recursive=true, Auto-Update=false, version=2" prefer="public" xml:base="">

        <uri name="http://emmo.info/emmo/1.0.0-beta5/mereocausality"                  uri="../mereocausality/mereocausality.ttl"/>

        <uri name="http://emmo.info/emmo/1.0.0-beta5/perspectives"                    uri="../perspectives/perspectives.ttl"/>
        <uri name="http://emmo.info/emmo/1.0.0-beta5/perspectives/perspective"        uri="../perspectives/perspective.ttl"/>
        <uri name="http://emmo.info/emmo/1.0.0-beta5/perspectives/semiotics"          uri="../perspectives/semiotics.ttl"/>
        <uri name="http://emmo.info/emmo/1.0.0-beta5/perspectives/perceptual"         uri="../perspectives/perceptual.ttl"/>
        <uri name="http://emmo.info/emmo/1.0.0-beta5/perspectives/reductionistic"     uri="../perspectives/reductionistic.ttl"/>
        <uri name="http://emmo.info/emmo/1.0.0-beta5/perspectives/holistic"           uri="../perspectives/holistic.ttl"/>
        <uri name="http://emmo.info/emmo/1.0.0-beta5/perspectives/persistence"        uri="../perspectives/persistence.ttl"/>
        <uri name="http://emmo.info/emmo/1.0.0-beta5/perspectives/physicalistic"      uri="../perspectives/physicalistic.ttl"/>
        <uri name="http://emmo.info/emmo/1.0.0-beta5/perspectives/standardmodel"      uri="../perspectives/standardmodel.ttl"/>
        <uri name="http://emmo.info/emmo/1.0.0-beta5/perspectives/data"               uri="../perspectives/data.ttl"/>

        <uri name="http://emmo.info/emmo/1.0.0-beta5/multiperspective"                uri="../multiperspective/multiperspective.ttl"/>
        <uri name="http://emmo.info/emmo/1.0.0-beta5/multiperspective/persholistic"   uri="../multiperspective/persholistic.ttl"/>
        <uri name="http://emmo.info/emmo/1.0.0-beta5/multiperspective/properties"     uri="../multiperspective/properties.ttl"/>
        <uri name="http://emmo.info/emmo/1.0.0-beta5/multiperspective/symbolic"       uri="../multiperspective/symbolic.ttl"/>
        <uri name="http://emmo.info/emmo/1.0.0-beta5/multiperspective/information"    uri="../multiperspective/information.ttl"/>
        <uri name="http://emmo.info/emmo/1.0.0-beta5/multiperspective/workflow"       uri="../multiperspective/workflow.ttl"/>

        <uri name="http://emmo.info/emmo/1.0.0-beta5/disciplines"                     uri="../disciplines/disciplines.ttl"/>
        <uri name="http://emmo.info/emmo/1.0.0-beta5/disciplines/chemistry"           uri="../disciplines/chemistry.ttl"/>
        <uri name="http://emmo.info/emmo/1.0.0-beta5/disciplines/computerscience"     uri="../disciplines/computerscience.ttl"/>
        <uri name="http://emmo.info/emmo/1.0.0-beta5/disciplines/manufacturing"       uri="../disciplines/manufacturing.ttl"/>
        <uri name="http://emmo.info/emmo/1.0.0-beta5/disciplines/materials"           uri="../disciplines/materials.ttl"/>
        <uri name="http://emmo.info/emmo/1.0.0-beta5/disciplines/math"                uri="../disciplines/math.ttl"/>
        <uri name="http://emmo.info/emmo/1.0.0-beta5/disciplines/models"              uri="../disciplines/models.ttl"/>
        <uri name="http://emmo.info/emmo/1.0.0-beta5/disciplines/periodictable"       uri="../disciplines/periodictable.ttl"/>

        <uri name="http://emmo.info/emmo/1.0.0-beta5/disciplines/metrology"           uri="../disciplines/metrology.ttl"/>
        <uri name="http://emmo.info/emmo/1.0.0-beta5/disciplines/isq"                 uri="../disciplines/isq.ttl"/>

        <uri name="http://emmo.info/emmo/1.0.0-beta5/disciplines/sysystem"            uri="../disciplines/sisystem.ttl"/>
        <uri name="http://emmo.info/emmo/1.0.0-beta5/disciplines/units/sidimensionalunits"  uri="../disciplines/units/sidimensionalunits.ttl"/>
        <uri name="http://emmo.info/emmo/1.0.0-beta5/disciplines/units/siunits"             uri="../disciplines/units/siunits.ttl"/>
        <uri name="http://emmo.info/emmo/1.0.0-beta5/disciplines/units/coherentsiunits"     uri="../disciplines/units/coherentsiunits.ttl"/>
        <uri name="http://emmo.info/emmo/1.0.0-beta5/disciplines/units/noncoherentsiunits"  uri="../disciplines/units/noncoherentsiunits.ttl"/>
        <uri name="http://emmo.info/emmo/1.0.0-beta5/disciplines/units/prefixedsiunits"     uri="../disciplines/units/prefixedsiunits.ttl"/>
        <uri name="http://emmo.info/emmo/1.0.0-beta5/disciplines/units/siacceptedunits"     uri="../disciplines/units/siacceptedunits.ttl"/>
        <uri name="http://emmo.info/emmo/1.0.0-beta5/disciplines/units/unclassifiedunits"   uri="../disciplines/units/unclassifiedunits.ttl"/>

        <!-- to be removed -->
        <uri name="http://emmo.info/emmo/1.0.0-beta5/disciplines/unitsextension"      uri="../disciplines/units/unitsextension.ttl"/>
        <uri name="http://emmo.info/emmo/1.0.0-beta5/disciplines/prefixedunits"       uri="../disciplines/units/prefixedunits.ttl"/>
        <uri name="http://emmo.info/emmo/1.0.0-beta5/disciplines/deprecated"          uri="../disciplines/units/deprecated.ttl"/>

    </group>
</catalog>
